rply/__init__.py
rply/errors.py
rply/lexergenerator.py
rply/parsergenerator.py
rply/token.py
rply/分词器.py
rply/分词器母机.py
rply/功用.py
rply/报错.py
rply/词.py
rply/语法.py
rply/语法分析器.py
rply/语法分析器母机.py
rply_ulang-0.8.4.dist-info/LICENSE
rply_ulang-0.8.4.dist-info/METADATA
rply_ulang-0.8.4.dist-info/WHEEL
rply_ulang-0.8.4.dist-info/top_level.txt
rply_ulang-0.8.4.dist-info/RECORD
