Metadata-Version: 2.1
Name: rply-ulang
Version: 0.8.4
Summary: RPly 木兰编程语言定制版
Home-page: UNKNOWN
Author: Xuan Wu
Author-email: mulanrevive@gmail.com
License: BSD 3-Clause License
Project-URL: Source, https://github.com/nobodxbodon/rply
Platform: UNKNOWN
Requires-Dist: appdirs
